.gitignore
.readthedocs.yaml
Cargo.lock
Cargo.toml
LICENSE
MANIFEST.in
README.md
build-wheels.sh
config.toml
pyproject.toml
requirements.txt
setup.py
docs/Makefile
docs/conf.py
docs/index.rst
docs/installation.md
docs/make.bat
docs/modules.rst
docs/nnv_py.constellation.rst
docs/nnv_py.dnn.rst
docs/nnv_py.nnv_py.rst
docs/nnv_py.rst
docs/requirements.txt
docs/rl_example.md
nnv_py/__init__.py
nnv_py/_version.py
nnv_py/asterism.py
nnv_py/dnn.py
nnv_py/starset.py
nnv_py/util.py
nnv_py.egg-info/PKG-INFO
nnv_py.egg-info/SOURCES.txt
nnv_py.egg-info/dependency_links.txt
nnv_py.egg-info/not-zip-safe
nnv_py.egg-info/requires.txt
nnv_py.egg-info/top_level.txt
nnv_py/__tests__/test_constellation.py
src/lib.rs